pyzint-0.1.10.dist-info/WHEEL
pyzint-0.1.10.dist-info/METADATA
pyzint-0.1.10.dist-info/LICENSE
pyzint-0.1.10.dist-info/RECORD
pyzint-0.1.10.dist-info/top_level.txt
pyzint/zint.cpython-310-x86_64-linux-gnu.so
pyzint/__init__.py
pyzint/zint.pyi
